{
  "nodes": [
    {
      "name": "CleanerService",
      "data": {
        "module": "examples.news_summarizer.agents.cleaner",
        "class_name": "CleanerService",
        "source_file": "/home/ubuntu/workbench/graphbus-core/examples/news_summarizer/agents/cleaner.py",
        "system_prompt": "\n    You clean and normalize text. In Build Mode you can propose\n    additional cleaning strategies like deduplication or sentiment filtering.\n    ",
        "methods": [
          "clean"
        ],
        "subscriptions": [
          "/News/Raw"
        ],
        "metadata": {}
      }
    },
    {
      "name": "FetcherService",
      "data": {
        "module": "examples.news_summarizer.agents.fetcher",
        "class_name": "FetcherService",
        "source_file": "/home/ubuntu/workbench/graphbus-core/examples/news_summarizer/agents/fetcher.py",
        "system_prompt": "\n    You fetch news headlines. In Build Mode you can propose improvements\n    to how headlines are structured or filtered.\n    ",
        "methods": [
          "fetch_headlines"
        ],
        "subscriptions": [],
        "metadata": {}
      }
    },
    {
      "name": "FormatterService",
      "data": {
        "module": "examples.news_summarizer.agents.formatter",
        "class_name": "FormatterService",
        "source_file": "/home/ubuntu/workbench/graphbus-core/examples/news_summarizer/agents/formatter.py",
        "system_prompt": "\n    You format news digests. In Build Mode you can propose richer output\n    formats like markdown, HTML, or priority ordering.\n    ",
        "methods": [
          "format_digest"
        ],
        "subscriptions": [],
        "metadata": {}
      }
    },
    {
      "name": "/News/Raw",
      "data": {
        "node_type": "topic"
      }
    }
  ],
  "edges": [
    {
      "src": "CleanerService",
      "dst": "FetcherService",
      "data": {
        "edge_type": "schema_depends",
        "schema_info": {
          "inferred": true
        }
      }
    },
    {
      "src": "/News/Raw",
      "dst": "CleanerService",
      "data": {
        "edge_type": "subscribes"
      }
    }
  ]
}